adam/__init__.py
adam/io/__init__.py
adam/io/get_radar_scan.py
adam/model/__init__.py
adam/model/predict_lake_breeze.py
adam/util/__init__.py
adam/util/instrument_steering.py
adam/vis/__init__.py
adam/vis/visualize_lake_breeze.py
adam_atmos-0.3.1.dist-info/licenses/AUTHORS.rst
adam_atmos-0.3.1.dist-info/licenses/LICENSE
adam_atmos-0.3.1.dist-info/METADATA
adam_atmos-0.3.1.dist-info/WHEEL
adam_atmos-0.3.1.dist-info/top_level.txt
adam_atmos-0.3.1.dist-info/RECORD
