Metadata-Version: 2.4
Name: adam-atmos
Version: 0.3.1
Summary: A proof of concept for a digital twin for the Argonne Testbed for Multiscale Observational Studies. This initial package contains a model that determines the lakebreeze front location from the 0.5 degree scan of the NEXRAD radar.
Author-email: Robert Clyde Jackson <rjackson@anl.gov>
Maintainer-email: Robert Clyde Jackson <rjackson@anl.gov>
License: BSD license
Project-URL: bugs, https://github.com/rcjackson/adam/issues
Project-URL: changelog, https://github.com/rcjackson/adam/blob/master/changelog.md
Project-URL: homepage, https://github.com/rcjackson/adam
License-File: LICENSE
License-File: AUTHORS.rst
Requires-Dist: torchvision
Requires-Dist: torch
Requires-Dist: huggingface_hub
Requires-Dist: arm_pyart
Requires-Dist: safetensors
Requires-Dist: cartopy
Requires-Dist: boto3
Provides-Extra: dev
Requires-Dist: coverage; extra == "dev"
Requires-Dist: mypy; extra == "dev"
Requires-Dist: pytest; extra == "dev"
Requires-Dist: ruff; extra == "dev"
Requires-Dist: tox; extra == "dev"
Dynamic: license-file
